rabbit/__init__.py
rabbit/__main__.py
rabbit/_wait.py
rabbit/background_tasks.py
rabbit/client.py
rabbit/dlx.py
rabbit/exceptions.py
rabbit/exchange.py
rabbit/job.py
rabbit/logger.py
rabbit/publish.py
rabbit/queue.py
rabbit/subscribe.py
rabbit/cli/__init__.py
rabbit/cli/consumer.py
rabbit/cli/publisher.py
tests/__init__.py
tests/conftest.py
tests/unit/__init__.py
tests/unit/test_background_tasks.py
tests/unit/test_cli.py
tests/unit/test_client.py
tests/unit/test_dlx.py
tests/unit/test_exceptions.py
tests/unit/test_exchange.py
tests/unit/test_jobs.py
tests/unit/test_publish.py
tests/unit/test_queue.py
tests/unit/test_subscribe.py
tests/unit/test_wait.py
rabbit_client-3.3.0.dist-info/LICENSE
rabbit_client-3.3.0.dist-info/METADATA
rabbit_client-3.3.0.dist-info/WHEEL
rabbit_client-3.3.0.dist-info/entry_points.txt
rabbit_client-3.3.0.dist-info/top_level.txt
rabbit_client-3.3.0.dist-info/RECORD
