Metadata-Version: 2.1
Name: rabbit-client
Version: 3.3.0
Summary: async rabbit client
Home-page: https://github.com/amenezes/rabbit-client
Author: Alexandre Menezes
Author-email: alexandre.fmenezes@gmail.com
License: Apache-2.0
Project-URL: Documentation, https://rabbit-client.amenezes.net
Project-URL: Code, https://github.com/amenezes/rabbit-client
Project-URL: Issue tracker, https://github.com/amenezes/rabbit-client/issues
Project-URL: Changes, https://github.com/amenezes/rabbit-client/releases
Keywords: "asyncio","aioamqp","amqp","rabbitmq"
Classifier: Programming Language :: Python :: 3 :: Only
Classifier: Programming Language :: Python :: 3.8
Classifier: Programming Language :: Python :: 3.9
Classifier: Programming Language :: Python :: 3.10
Classifier: Programming Language :: Python :: 3.11
Classifier: Programming Language :: Python :: 3.12
Classifier: Framework :: AsyncIO
Classifier: Development Status :: 5 - Production/Stable
Classifier: Intended Audience :: Developers
Classifier: License :: OSI Approved :: Apache Software License
Classifier: Operating System :: OS Independent
Classifier: Programming Language :: Python :: Implementation :: CPython
Classifier: Topic :: Software Development :: Libraries
Classifier: Topic :: Software Development :: Object Brokering
Classifier: Topic :: System :: Distributed Computing
Requires-Python: >=3.8.0
License-File: LICENSE
Requires-Dist: aioamqp >=0.15.0
Requires-Dist: attrs >=19.1.0
Provides-Extra: all
Requires-Dist: click >=8.1.3 ; extra == 'all'
Requires-Dist: rich >=12.6.0 ; extra == 'all'
Requires-Dist: trogon >=0.5.0 ; extra == 'all'
Provides-Extra: cli
Requires-Dist: click >=8.1.3 ; extra == 'cli'
Requires-Dist: rich >=12.6.0 ; extra == 'cli'
Requires-Dist: trogon >=0.5.0 ; extra == 'cli'
